time_converter/__init__.py
time_converter/generate_spice_files.py
time_converter/converters/__init__.py
time_converter/converters/earth.py
time_converter/converters/change4/__init__.py
time_converter/converters/change4/change4_localtime.dat
time_converter/converters/msl/__init__.py
time_converter/converters/msl/chronos.py
time_converter/converters/msl/msl.tsc
time_converter/tests/__init__.py
time_converter/tests/test_time_converter.py
time_converter-1.1.4.dist-info/LICENSE
time_converter-1.1.4.dist-info/METADATA
time_converter-1.1.4.dist-info/WHEEL
time_converter-1.1.4.dist-info/top_level.txt
time_converter-1.1.4.dist-info/RECORD
