Metadata-Version: 2.1
Name: time-converter
Version: 1.1.4
Summary: A Python class that allows for convenient conversion between different date and time formats/units
Home-page: https://gitlab.physik.uni-kiel.de/ET/time_converter
Author: Johan von Forstner
Author-email: forstner@physik.uni-kiel.de
License: UNKNOWN
Platform: UNKNOWN
Classifier: Programming Language :: Python :: 3
Classifier: License :: OSI Approved :: MIT License
Classifier: Operating System :: OS Independent
Requires-Dist: numpy
Provides-Extra: dev
Requires-Dist: pytest ; extra == 'dev'
Requires-Dist: pytest-cov ; extra == 'dev'
Requires-Dist: numpydoc ; extra == 'dev'
Requires-Dist: Sphinx ; extra == 'dev'
